[
  {
    "nama": "HTML",
    "level": "Advanced",
    "image": "/assets/html_logo.webp"
  },
  {
    "nama": "CSS",
    "level": "Advanced",
    "image": "/assets/css_logo.webp"
  },
  {
    "nama": "JavaScript",
    "level": "Advanced",
    "image": "/assets/javascript_logo.webp"
  },
  {
    "nama": "TypeScript",
    "level": "Advanced",
    "image": "/assets/typescript_logo.webp"
  },
  {
    "nama": "PHP",
    "level": "Advanced",
    "image": "/assets/php_logo.webp"
  },
  {
    "nama": "CodeIgniter",
    "level": "Intermediate",
    "image": "/assets/codeigniter_logo.webp"
  },
  {
    "nama": "Laravel",
    "level": "Intermediate",
    "image": "/assets/laravel_logo.webp"
  },
  {
    "nama": "React",
    "level": "Advanced",
    "image": "/assets/react_logo.webp"
  },
  {
    "nama": "Express",
    "level": "Intermediate",
    "image": "/assets/express_logo.webp"
  },
  {
    "nama": "Webpack",
    "level": "Intermediate",
    "image": "/assets/webpack.webp"
  },
  {
    "nama": "PWA",
    "level": "Intermediate",
    "image": "/assets/pwa_icon.webp"
  },
  {
    "nama": "Vite",
    "level": "Intermediate",
    "image": "/assets/vite_logo.webp"
  },
  {
    "nama": "Node JS",
    "level": "Intermediate",
    "image": "/assets/nodejs_logo.webp"
  },
  {
    "nama": "Bootstrap",
    "level": "Advanced",
    "image": "/assets/bootstrap_logo.webp"
  },
  {
    "nama": "Tailwind",
    "level": "Advanced",
    "image": "/assets/tailwind_logo.webp"
  },
  {
    "nama": "MySQL",
    "level": "Advanced",
    "image": "/assets/mysql.webp"
  },
  {
    "nama": "PostgreSQL",
    "level": "Intermediate",
    "image": "/assets/postgresql_logo.webp"
  },
  {
    "nama": "MsSQL",
    "level": "Intermediate",
    "image": "/assets/mssql.webp"
  },
  {
    "nama": "MongoDB",
    "level": "Intermediate",
    "image": "/assets/MongoDB_logo.webp"
  },
  {
    "nama": "Vue JS"
  },
  {
    "nama": "Next JS"
  }
]
